[{"SpriteId":0,"PrefabId":1,"WeaponType":0,"Name":"삽","DescType":0,"Desc":"데미지 {0}% 증가\n회전체 {1}개\n사거리 {2}","Projectile":[3,4,5,6,7,8,9,10],"Damage":[1.0,2.0,3.0,4.0,5.0,6.0,7.0,8.0],"Speed":[100.0,200.0,300.0,400.0,500.0,600.0,700.0,800.0],"Range":[1.0,1.2,1.4,1.6,1.8,2.0,2.2,2.4],"CoolTime":[0.0,0.0,0.0,0.0,0.0,0.0,0.0,0.0],"Pierce":[0,0,0,0,0,0,0,0]},{"SpriteId":1,"PrefabId":2,"WeaponType":1,"Name":"엽","DescType":1,"Desc":"데미지 {0}% 증가\n투사체 {1}\n쿨타임 {2} / 관통력{3}","Projectile":[1,1,2,2,3,3,4,4],"Damage":[1.0,2.0,3.0,4.0,5.0,6.0,7.0,8.0],"Speed":[10.0,12.0,14.0,16.0,18.0,20.0,22.0,24.0],"Range":[0.0,0.0,0.0,0.0,0.0,0.0,0.0,0.0],"CoolTime":[1.6,1.4,1.2,1.0,0.8,0.6,0.4,0.2],"Pierce":[1,2,3,4,5,6,7,8]}]